py-capsolver/__init__.py
py-capsolver/capsolvers.py
py-capsolver/exceptions.py
py-capsolver/hcaptcha.py
pycapsolver/__init__.py
pycapsolver/capsolvers.py
pycapsolver/exceptions.py
pycapsolver/hcaptcha.py
py_capsolver-0.0.3.dist-info/LICENSE
py_capsolver-0.0.3.dist-info/METADATA
py_capsolver-0.0.3.dist-info/WHEEL
py_capsolver-0.0.3.dist-info/top_level.txt
py_capsolver-0.0.3.dist-info/RECORD
