Metadata-Version: 2.1
Name: py-capsolver
Version: 0.0.3
Summary: capsolver wrappeer
Home-page: UNKNOWN
Author: Slotth
Author-email: slotth@outlook.com
License: UNKNOWN
Keywords: capsolver
Platform: UNKNOWN
Classifier: Development Status :: 5 - Production/Stable
Classifier: Intended Audience :: Education
Classifier: Operating System :: Microsoft :: Windows :: Windows 10
Classifier: License :: OSI Approved :: MIT License
Classifier: Programming Language :: Python :: 3
